autosuggest_client/__init__.py
autosuggest_client/_auto_suggest_client.py
autosuggest_client/_configuration.py
autosuggest_client/version.py
autosuggest_client/aio/__init__.py
autosuggest_client/aio/_auto_suggest_client.py
autosuggest_client/aio/_configuration.py
autosuggest_client/aio/operations/__init__.py
autosuggest_client/aio/operations/_auto_suggest_client_operations.py
autosuggest_client/models/__init__.py
autosuggest_client/models/_auto_suggest_client_enums.py
autosuggest_client/models/_models.py
autosuggest_client/operations/__init__.py
autosuggest_client/operations/_auto_suggest_client_operations.py
microsoft_bing_autosuggest-1.0.0.dist-info/LICENSE.txt
microsoft_bing_autosuggest-1.0.0.dist-info/METADATA
microsoft_bing_autosuggest-1.0.0.dist-info/WHEEL
microsoft_bing_autosuggest-1.0.0.dist-info/top_level.txt
microsoft_bing_autosuggest-1.0.0.dist-info/RECORD
